[
  {
    "title":"Database",
    "urls":[
      { "url":"http://www.commentcamarche.net/contents/104-bases-de-donnees-introduction",
        "description":"Useful link to begin with database."
      },
      { "url":"http://openclassrooms.com/courses/concevez-votre-site-web-avec-php-et-mysql/tp-un-mini-chat",
        "description":"Tutorial to use it and try to build one."
      }
    ]
  },
  {
    "title":"Password security",
    "urls":[
      { "url":"http://fr.wikipedia.org/wiki/Attaque_par_force_brute",
        "description":"Wikipedia link which explain the brute force approch"
      }
    ]
  }
]